daggr/CHANGELOG.md
daggr/__init__.py
daggr/_client_cache.py
daggr/_utils.py
daggr/cli.py
daggr/edge.py
daggr/executor.py
daggr/graph.py
daggr/local_space.py
daggr/node.py
daggr/ops.py
daggr/package.json
daggr/port.py
daggr/py.typed
daggr/server.py
daggr/session.py
daggr/state.py
daggr/assets/hf-logo-pirate.png
daggr/assets/logo_dark.png
daggr/assets/logo_dark_small.png
daggr/assets/logo_light.png
daggr/frontend/dist/index.html
daggr/frontend/dist/assets/EXT_lights_area-C2KLLBqV.js
daggr/frontend/dist/assets/EXT_lights_ies-C_88Oiym.js
daggr/frontend/dist/assets/EXT_lights_image_based-B3BzuyG-.js
daggr/frontend/dist/assets/EXT_mesh_gpu_instancing-DXxDXZ0e.js
daggr/frontend/dist/assets/EXT_meshopt_compression-g7Dc-tNL.js
daggr/frontend/dist/assets/EXT_texture_avif-CFRHTKQO.js
daggr/frontend/dist/assets/EXT_texture_webp-Be-AL7iu.js
daggr/frontend/dist/assets/ExtrasAsMetadata-BRTx057p.js
daggr/frontend/dist/assets/KHR_animation_pointer-WUOb1wUh.js
daggr/frontend/dist/assets/KHR_draco_mesh_compression-mUeVa0GD.js
daggr/frontend/dist/assets/KHR_interactivity-0REspvdU.js
daggr/frontend/dist/assets/KHR_lights_punctual-Ct1dTA_f.js
daggr/frontend/dist/assets/KHR_materials_anisotropy-lPjRdcEw.js
daggr/frontend/dist/assets/KHR_materials_clearcoat-CHbdTKVd.js
daggr/frontend/dist/assets/KHR_materials_diffuse_roughness-beTCCFQz.js
daggr/frontend/dist/assets/KHR_materials_diffuse_transmission-CjQq9YXS.js
daggr/frontend/dist/assets/KHR_materials_dispersion-JzlBn_oa.js
daggr/frontend/dist/assets/KHR_materials_emissive_strength-BMNxmw_s.js
daggr/frontend/dist/assets/KHR_materials_ior-DpQeQwyQ.js
daggr/frontend/dist/assets/KHR_materials_iridescence-w4Ie439b.js
daggr/frontend/dist/assets/KHR_materials_pbrSpecularGlossiness-CdQXjSwb.js
daggr/frontend/dist/assets/KHR_materials_sheen-DWCSBtu3.js
daggr/frontend/dist/assets/KHR_materials_specular-CIIi3DrU.js
daggr/frontend/dist/assets/KHR_materials_transmission-vgfM8J8n.js
daggr/frontend/dist/assets/KHR_materials_unlit-hllV5Iwm.js
daggr-0.5.4.dist-info/METADATA
daggr-0.5.4.dist-info/WHEEL
daggr-0.5.4.dist-info/entry_points.txt
daggr-0.5.4.dist-info/licenses/LICENSE
daggr-0.5.4.dist-info/RECORD
