Metadata-Version: 2.4
Name: daggr
Version: 0.5.4
Summary: A Python package
Project-URL: homepage, https://github.com/abidlabs/daggr
Project-URL: repository, https://github.com/abidlabs/daggr
Author-email: Abubakar Abid <abubakar@example.com>
License-File: LICENSE
Classifier: License :: OSI Approved :: MIT License
Classifier: Operating System :: OS Independent
Classifier: Programming Language :: Python :: 3
Requires-Python: >=3.10
Requires-Dist: fastapi>=0.115.0
Requires-Dist: gradio>=6.0.0
Requires-Dist: networkx>=3.0
Requires-Dist: uvicorn[standard]>=0.34.0
Provides-Extra: dev
Requires-Dist: pytest<9.0.0,>=8.0.0; extra == 'dev'
Requires-Dist: ruff==0.9.3; extra == 'dev'
